codesnipper/__init__.py
codesnipper/codesnipper.py
code_snipper-0.1.14.dist-info/METADATA
code_snipper-0.1.14.dist-info/WHEEL
code_snipper-0.1.14.dist-info/top_level.txt
code_snipper-0.1.14.dist-info/RECORD
