Metadata-Version: 2.1
Name: code-snipper
Version: 0.1.14
Summary: Snip out code section from a string or text file
Author: Mohit Sharma
License: BSD-3-Clause
Keywords: code-extractor,two
Classifier: Programming Language :: Python :: 3
Requires-Python: >=3.9
Requires-Dist: pydantic
